{
  "openapi": "3.0.1",
  "info": {
    "title": "SplitWebService",
    "version": "1.0"
  },
  "paths": {
    "/Expense": {
      "get": {
        "tags": [
          "Expense"
        ],
        "operationId": "GetExpense",
        "parameters": [
          {
            "name": "id",
            "in": "query",
            "style": "form",
            "schema": {
              "type": "string",
              "format": "uuid"
            }
          }
        ],
        "responses": {
          "200": {
            "description": "Success",
            "content": {
              "application/json": {
                "schema": {
                  "$ref": "#/components/schemas/ExpenseServiceResponse"
                }
              }
            }
          }
        }
      }
    },
    "/GroupExpenses": {
      "get": {
        "tags": [
          "Expense"
        ],
        "operationId": "GetGroupExpenses",
        "parameters": [
          {
            "name": "groupId",
            "in": "query",
            "style": "form",
            "schema": {
              "type": "string",
              "format": "uuid"
            }
          }
        ],
        "responses": {
          "200": {
            "description": "Success",
            "content": {
              "application/json": {
                "schema": {
                  "$ref": "#/components/schemas/ExpenseListServiceResponse"
                }
              }
            }
          }
        }
      }
    },
    "/UserExpenses": {
      "get": {
        "tags": [
          "Expense"
        ],
        "operationId": "GetUserExpenses",
        "parameters": [
          {
            "name": "userId",
            "in": "query",
            "style": "form",
            "schema": {
              "type": "integer",
              "format": "int32"
            }
          }
        ],
        "responses": {
          "200": {
            "description": "Success",
            "content": {
              "application/json": {
                "schema": {
                  "$ref": "#/components/schemas/ExpenseListServiceResponse"
                }
              }
            }
          }
        }
      }
    },
    "/AddExpense": {
      "post": {
        "tags": [
          "Expense"
        ],
        "operationId": "AddExpense",
        "parameters": [
          {
            "name": "name",
            "in": "query",
            "style": "form",
            "schema": {
              "type": "string"
            }
          },
          {
            "name": "userId",
            "in": "query",
            "style": "form",
            "schema": {
              "type": "integer",
              "format": "int32"
            }
          },
          {
            "name": "groupId",
            "in": "query",
            "style": "form",
            "schema": {
              "type": "string",
              "format": "uuid"
            }
          },
          {
            "name": "sum",
            "in": "query",
            "style": "form",
            "schema": {
              "type": "number",
              "format": "double"
            }
          },
          {
            "name": "date",
            "in": "query",
            "style": "form",
            "schema": {
              "type": "string",
              "format": "date-time"
            }
          }
        ],
        "responses": {
          "200": {
            "description": "Success",
            "content": {
              "application/json": {
                "schema": {
                  "$ref": "#/components/schemas/ExpenseServiceResponse"
                }
              }
            }
          }
        }
      }
    },
    "/DeleteExpense": {
      "delete": {
        "tags": [
          "Expense"
        ],
        "operationId": "DeleteExpense",
        "parameters": [
          {
            "name": "id",
            "in": "query",
            "style": "form",
            "schema": {
              "type": "string",
              "format": "uuid"
            }
          }
        ],
        "responses": {
          "200": {
            "description": "Success"
          }
        }
      }
    },
    "/Debt": {
      "get": {
        "tags": [
          "Expense"
        ],
        "operationId": "GetDebt",
        "parameters": [
          {
            "name": "id",
            "in": "query",
            "style": "form",
            "schema": {
              "type": "string",
              "format": "uuid"
            }
          }
        ],
        "responses": {
          "200": {
            "description": "Success",
            "content": {
              "application/json": {
                "schema": {
                  "$ref": "#/components/schemas/DebtModelServiceResponse"
                }
              }
            }
          }
        }
      }
    },
    "/UserDebts": {
      "get": {
        "tags": [
          "Expense"
        ],
        "operationId": "GetUserDebts",
        "parameters": [
          {
            "name": "userId",
            "in": "query",
            "style": "form",
            "schema": {
              "type": "integer",
              "format": "int32"
            }
          }
        ],
        "responses": {
          "200": {
            "description": "Success",
            "content": {
              "application/json": {
                "schema": {
                  "$ref": "#/components/schemas/DebtModelListServiceResponse"
                }
              }
            }
          }
        }
      }
    },
    "/ExpenseDebts": {
      "get": {
        "tags": [
          "Expense"
        ],
        "operationId": "GetExpenseDebts",
        "parameters": [
          {
            "name": "expenseId",
            "in": "query",
            "style": "form",
            "schema": {
              "type": "string",
              "format": "uuid"
            }
          }
        ],
        "responses": {
          "200": {
            "description": "Success",
            "content": {
              "application/json": {
                "schema": {
                  "$ref": "#/components/schemas/DebtModelListServiceResponse"
                }
              }
            }
          }
        }
      }
    },
    "/AddDebt": {
      "post": {
        "tags": [
          "Expense"
        ],
        "operationId": "AddDebt",
        "parameters": [
          {
            "name": "expenseId",
            "in": "query",
            "style": "form",
            "schema": {
              "type": "string",
              "format": "uuid"
            }
          },
          {
            "name": "userId",
            "in": "query",
            "style": "form",
            "schema": {
              "type": "integer",
              "format": "int32"
            }
          },
          {
            "name": "sum",
            "in": "query",
            "style": "form",
            "schema": {
              "type": "number",
              "format": "double"
            }
          },
          {
            "name": "paid",
            "in": "query",
            "style": "form",
            "schema": {
              "type": "number",
              "format": "double"
            }
          }
        ],
        "responses": {
          "200": {
            "description": "Success",
            "content": {
              "application/json": {
                "schema": {
                  "$ref": "#/components/schemas/DebtModelServiceResponse"
                }
              }
            }
          }
        }
      }
    },
    "/DeleteDebt": {
      "delete": {
        "tags": [
          "Expense"
        ],
        "operationId": "DeleteDebt",
        "parameters": [
          {
            "name": "id",
            "in": "query",
            "style": "form",
            "schema": {
              "type": "string",
              "format": "uuid"
            }
          }
        ],
        "responses": {
          "200": {
            "description": "Success"
          }
        }
      }
    },
    "/UserGroupDebts": {
      "get": {
        "tags": [
          "Expense"
        ],
        "operationId": "GetUserGroupDebts",
        "parameters": [
          {
            "name": "groupId",
            "in": "query",
            "style": "form",
            "schema": {
              "type": "string",
              "format": "uuid"
            }
          },
          {
            "name": "userId",
            "in": "query",
            "style": "form",
            "schema": {
              "type": "integer",
              "format": "int32"
            }
          }
        ],
        "responses": {
          "200": {
            "description": "Success",
            "content": {
              "application/json": {
                "schema": {
                  "$ref": "#/components/schemas/DebtModelListServiceResponse"
                }
              }
            }
          }
        }
      }
    },
    "/UserCustomDebts": {
      "get": {
        "tags": [
          "Expense"
        ],
        "operationId": "GetUserCustomDebts",
        "parameters": [
          {
            "name": "userId",
            "in": "query",
            "style": "form",
            "schema": {
              "type": "integer",
              "format": "int32"
            }
          },
          {
            "name": "debtUserId",
            "in": "query",
            "style": "form",
            "schema": {
              "type": "integer",
              "format": "int32"
            }
          }
        ],
        "responses": {
          "200": {
            "description": "Success",
            "content": {
              "application/json": {
                "schema": {
                  "$ref": "#/components/schemas/CustomDebtListServiceResponse"
                }
              }
            }
          }
        }
      }
    },
    "/UserGroupCustomDebts": {
      "get": {
        "tags": [
          "Expense"
        ],
        "operationId": "GetUserGroupCustomDebts",
        "parameters": [
          {
            "name": "groupId",
            "in": "query",
            "style": "form",
            "schema": {
              "type": "string",
              "format": "uuid"
            }
          },
          {
            "name": "debtUserId",
            "in": "query",
            "style": "form",
            "schema": {
              "type": "integer",
              "format": "int32"
            }
          },
          {
            "name": "userId",
            "in": "query",
            "style": "form",
            "schema": {
              "type": "integer",
              "format": "int32"
            }
          }
        ],
        "responses": {
          "200": {
            "description": "Success",
            "content": {
              "application/json": {
                "schema": {
                  "$ref": "#/components/schemas/CustomDebtListServiceResponse"
                }
              }
            }
          }
        }
      }
    },
    "/PayDebt": {
      "patch": {
        "tags": [
          "Expense"
        ],
        "operationId": "PayDebt",
        "parameters": [
          {
            "name": "debtId",
            "in": "query",
            "style": "form",
            "schema": {
              "type": "string",
              "format": "uuid"
            }
          },
          {
            "name": "paid",
            "in": "query",
            "style": "form",
            "schema": {
              "type": "number",
              "format": "double"
            }
          }
        ],
        "responses": {
          "200": {
            "description": "Success",
            "content": {
              "application/json": {
                "schema": {
                  "$ref": "#/components/schemas/DebtModelServiceResponse"
                }
              }
            }
          }
        }
      }
    },
    "/Groups": {
      "get": {
        "tags": [
          "Group"
        ],
        "operationId": "GetAllGroups",
        "responses": {
          "200": {
            "description": "Success",
            "content": {
              "application/json": {
                "schema": {
                  "$ref": "#/components/schemas/GroupListServiceResponse"
                }
              }
            }
          }
        }
      }
    },
    "/Group": {
      "get": {
        "tags": [
          "Group"
        ],
        "operationId": "GetGroup",
        "parameters": [
          {
            "name": "groupId",
            "in": "query",
            "style": "form",
            "schema": {
              "type": "string",
              "format": "uuid"
            }
          }
        ],
        "responses": {
          "200": {
            "description": "Success",
            "content": {
              "application/json": {
                "schema": {
                  "$ref": "#/components/schemas/GroupServiceResponse"
                }
              }
            }
          }
        }
      }
    },
    "/AddGroup": {
      "post": {
        "tags": [
          "Group"
        ],
        "operationId": "AddGroup",
        "parameters": [
          {
            "name": "name",
            "in": "query",
            "style": "form",
            "schema": {
              "type": "string"
            }
          },
          {
            "name": "adminId",
            "in": "query",
            "style": "form",
            "schema": {
              "type": "integer",
              "format": "int32"
            }
          },
          {
            "name": "description",
            "in": "query",
            "style": "form",
            "schema": {
              "type": "string"
            }
          }
        ],
        "responses": {
          "200": {
            "description": "Success",
            "content": {
              "application/json": {
                "schema": {
                  "$ref": "#/components/schemas/GroupServiceResponse"
                }
              }
            }
          },
          "400": {
            "description": "Bad Request"
          },
          "500": {
            "description": "Server Error"
          }
        }
      }
    },
    "/DeleteGroup": {
      "delete": {
        "tags": [
          "Group"
        ],
        "operationId": "DeleteGroup",
        "parameters": [
          {
            "name": "groupId",
            "in": "query",
            "style": "form",
            "schema": {
              "type": "string",
              "format": "uuid"
            }
          }
        ],
        "responses": {
          "200": {
            "description": "Success"
          }
        }
      }
    },
    "/UpdateName": {
      "patch": {
        "tags": [
          "Group"
        ],
        "operationId": "UpdateName",
        "parameters": [
          {
            "name": "groupId",
            "in": "query",
            "style": "form",
            "schema": {
              "type": "string",
              "format": "uuid"
            }
          },
          {
            "name": "name",
            "in": "query",
            "style": "form",
            "schema": {
              "type": "string"
            }
          }
        ],
        "responses": {
          "200": {
            "description": "Success",
            "content": {
              "application/json": {
                "schema": {
                  "$ref": "#/components/schemas/GroupServiceResponse"
                }
              }
            }
          }
        }
      }
    },
    "/UpdateDescription": {
      "patch": {
        "tags": [
          "Group"
        ],
        "operationId": "UpdateDescription",
        "parameters": [
          {
            "name": "groupId",
            "in": "query",
            "style": "form",
            "schema": {
              "type": "string",
              "format": "uuid"
            }
          },
          {
            "name": "description",
            "in": "query",
            "style": "form",
            "schema": {
              "type": "string"
            }
          }
        ],
        "responses": {
          "200": {
            "description": "Success",
            "content": {
              "application/json": {
                "schema": {
                  "$ref": "#/components/schemas/GroupServiceResponse"
                }
              }
            }
          }
        }
      }
    },
    "/Members": {
      "get": {
        "tags": [
          "Group"
        ],
        "operationId": "GetGroupMembers",
        "parameters": [
          {
            "name": "groupId",
            "in": "query",
            "style": "form",
            "schema": {
              "type": "string",
              "format": "uuid"
            }
          }
        ],
        "responses": {
          "200": {
            "description": "Success",
            "content": {
              "application/json": {
                "schema": {
                  "$ref": "#/components/schemas/GroupMemberListServiceResponse"
                }
              }
            }
          }
        }
      }
    },
    "/AddUserToGroup": {
      "post": {
        "tags": [
          "Group"
        ],
        "operationId": "AddUserToGroup",
        "parameters": [
          {
            "name": "groupId",
            "in": "query",
            "style": "form",
            "schema": {
              "type": "string",
              "format": "uuid"
            }
          },
          {
            "name": "userId",
            "in": "query",
            "style": "form",
            "schema": {
              "type": "integer",
              "format": "int32"
            }
          }
        ],
        "responses": {
          "200": {
            "description": "Success"
          },
          "400": {
            "description": "Bad Request"
          },
          "500": {
            "description": "Server Error"
          }
        }
      }
    },
    "/DeleteGroupMember": {
      "delete": {
        "tags": [
          "Group"
        ],
        "operationId": "DeleteGroupMember",
        "parameters": [
          {
            "name": "groupId",
            "in": "query",
            "style": "form",
            "schema": {
              "type": "string",
              "format": "uuid"
            }
          },
          {
            "name": "userId",
            "in": "query",
            "style": "form",
            "schema": {
              "type": "integer",
              "format": "int32"
            }
          }
        ],
        "responses": {
          "200": {
            "description": "Success"
          }
        }
      }
    },
    "/UserGroups": {
      "get": {
        "tags": [
          "Group"
        ],
        "operationId": "GetUserGroups",
        "parameters": [
          {
            "name": "userId",
            "in": "query",
            "style": "form",
            "schema": {
              "type": "integer",
              "format": "int32"
            }
          }
        ],
        "responses": {
          "200": {
            "description": "Success",
            "content": {
              "application/json": {
                "schema": {
                  "$ref": "#/components/schemas/GroupListServiceResponse"
                }
              }
            }
          }
        }
      }
    },
    "/Roles": {
      "get": {
        "tags": [
          "Role"
        ],
        "operationId": "GetAllRoles",
        "responses": {
          "200": {
            "description": "Success",
            "content": {
              "application/json": {
                "schema": {
                  "$ref": "#/components/schemas/RoleListServiceResponse"
                }
              }
            }
          }
        }
      }
    },
    "/SetRole": {
      "post": {
        "tags": [
          "Role"
        ],
        "operationId": "SetRole",
        "parameters": [
          {
            "name": "userId",
            "in": "query",
            "style": "form",
            "schema": {
              "type": "integer",
              "format": "int32"
            }
          },
          {
            "name": "roleName",
            "in": "query",
            "style": "form",
            "schema": {
              "type": "string"
            }
          },
          {
            "name": "groupId",
            "in": "query",
            "style": "form",
            "schema": {
              "type": "string",
              "format": "uuid"
            }
          }
        ],
        "responses": {
          "200": {
            "description": "Success"
          }
        }
      }
    },
    "/RemoveRole": {
      "delete": {
        "tags": [
          "Role"
        ],
        "operationId": "RemoveRole",
        "parameters": [
          {
            "name": "userId",
            "in": "query",
            "style": "form",
            "schema": {
              "type": "integer",
              "format": "int32"
            }
          },
          {
            "name": "roleName",
            "in": "query",
            "style": "form",
            "schema": {
              "type": "string"
            }
          },
          {
            "name": "groupId",
            "in": "query",
            "style": "form",
            "schema": {
              "type": "string",
              "format": "uuid"
            }
          }
        ],
        "responses": {
          "200": {
            "description": "Success"
          }
        }
      }
    },
    "/AddRole": {
      "post": {
        "tags": [
          "Role"
        ],
        "operationId": "AddRole",
        "requestBody": {
          "content": {
            "application/json": {
              "schema": {
                "allOf": [
                  {
                    "$ref": "#/components/schemas/AddRoleRequest"
                  }
                ]
              }
            },
            "text/json": {
              "schema": {
                "allOf": [
                  {
                    "$ref": "#/components/schemas/AddRoleRequest"
                  }
                ]
              }
            },
            "application/*+json": {
              "schema": {
                "allOf": [
                  {
                    "$ref": "#/components/schemas/AddRoleRequest"
                  }
                ]
              }
            }
          }
        },
        "responses": {
          "200": {
            "description": "Success",
            "content": {
              "application/json": {
                "schema": {
                  "$ref": "#/components/schemas/RoleServiceResponse"
                }
              }
            }
          },
          "400": {
            "description": "Bad Request"
          },
          "500": {
            "description": "Server Error"
          }
        }
      }
    },
    "/DeleteRole": {
      "delete": {
        "tags": [
          "Role"
        ],
        "operationId": "DeleteRole",
        "parameters": [
          {
            "name": "roleName",
            "in": "query",
            "style": "form",
            "schema": {
              "type": "string"
            }
          }
        ],
        "responses": {
          "200": {
            "description": "Success"
          }
        }
      }
    },
    "/User": {
      "get": {
        "tags": [
          "User"
        ],
        "operationId": "GetAllUsers",
        "responses": {
          "200": {
            "description": "Success",
            "content": {
              "application/json": {
                "schema": {
                  "$ref": "#/components/schemas/UserListServiceResponse"
                }
              }
            }
          }
        }
      }
    },
    "/User/{id}": {
      "get": {
        "tags": [
          "User"
        ],
        "operationId": "GetUserById",
        "parameters": [
          {
            "name": "id",
            "in": "path",
            "required": true,
            "style": "simple",
            "schema": {
              "type": "integer",
              "format": "int32"
            }
          }
        ],
        "responses": {
          "200": {
            "description": "Success",
            "content": {
              "application/json": {
                "schema": {
                  "$ref": "#/components/schemas/UserServiceResponse"
                }
              }
            }
          }
        }
      }
    },
    "/GetByLogin": {
      "get": {
        "tags": [
          "User"
        ],
        "operationId": "GetUserByLogin",
        "parameters": [
          {
            "name": "login",
            "in": "query",
            "style": "form",
            "schema": {
              "type": "string"
            }
          }
        ],
        "responses": {
          "200": {
            "description": "Success",
            "content": {
              "application/json": {
                "schema": {
                  "$ref": "#/components/schemas/UserServiceResponse"
                }
              }
            }
          }
        }
      }
    },
    "/auth": {
      "get": {
        "tags": [
          "User"
        ],
        "operationId": "Authorize",
        "parameters": [
          {
            "name": "login",
            "in": "query",
            "style": "form",
            "schema": {
              "type": "string"
            }
          },
          {
            "name": "password",
            "in": "query",
            "style": "form",
            "schema": {
              "type": "string"
            }
          }
        ],
        "responses": {
          "200": {
            "description": "Success",
            "content": {
              "application/json": {
                "schema": {
                  "$ref": "#/components/schemas/UserServiceResponse"
                }
              }
            }
          }
        }
      }
    },
    "/reg": {
      "post": {
        "tags": [
          "User"
        ],
        "operationId": "Register",
        "parameters": [
          {
            "name": "login",
            "in": "query",
            "style": "form",
            "schema": {
              "type": "string"
            }
          },
          {
            "name": "password",
            "in": "query",
            "style": "form",
            "schema": {
              "type": "string"
            }
          },
          {
            "name": "email",
            "in": "query",
            "style": "form",
            "schema": {
              "type": "string"
            }
          }
        ],
        "responses": {
          "200": {
            "description": "Success",
            "content": {
              "application/json": {
                "schema": {
                  "$ref": "#/components/schemas/UserServiceResponse"
                }
              }
            }
          }
        }
      }
    },
    "/updUserData": {
      "patch": {
        "tags": [
          "User"
        ],
        "operationId": "UpdateUserData",
        "parameters": [
          {
            "name": "id",
            "in": "query",
            "style": "form",
            "schema": {
              "type": "integer",
              "format": "int32"
            }
          },
          {
            "name": "login",
            "in": "query",
            "style": "form",
            "schema": {
              "type": "string"
            }
          },
          {
            "name": "email",
            "in": "query",
            "style": "form",
            "schema": {
              "type": "string"
            }
          },
          {
            "name": "password",
            "in": "query",
            "style": "form",
            "schema": {
              "type": "string"
            }
          }
        ],
        "responses": {
          "200": {
            "description": "Success",
            "content": {
              "application/json": {
                "schema": {
                  "$ref": "#/components/schemas/UserServiceResponse"
                }
              }
            }
          }
        }
      }
    },
    "/delete": {
      "delete": {
        "tags": [
          "User"
        ],
        "operationId": "Delete",
        "parameters": [
          {
            "name": "id",
            "in": "query",
            "style": "form",
            "schema": {
              "type": "integer",
              "format": "int32"
            }
          }
        ],
        "responses": {
          "200": {
            "description": "Success"
          }
        }
      }
    },
    "/Friend": {
      "get": {
        "tags": [
          "User"
        ],
        "operationId": "GetFriend",
        "parameters": [
          {
            "name": "userId",
            "in": "query",
            "style": "form",
            "schema": {
              "type": "integer",
              "format": "int32"
            }
          },
          {
            "name": "friendId",
            "in": "query",
            "style": "form",
            "schema": {
              "type": "integer",
              "format": "int32"
            }
          }
        ],
        "responses": {
          "200": {
            "description": "Success",
            "content": {
              "application/json": {
                "schema": {
                  "$ref": "#/components/schemas/FriendServiceResponse"
                }
              }
            }
          }
        }
      }
    },
    "/AddFriend": {
      "post": {
        "tags": [
          "User"
        ],
        "operationId": "AddFriend",
        "parameters": [
          {
            "name": "userId",
            "in": "query",
            "style": "form",
            "schema": {
              "type": "integer",
              "format": "int32"
            }
          },
          {
            "name": "friendId",
            "in": "query",
            "style": "form",
            "schema": {
              "type": "integer",
              "format": "int32"
            }
          },
          {
            "name": "request",
            "in": "query",
            "style": "form",
            "schema": {
              "type": "boolean"
            }
          }
        ],
        "responses": {
          "200": {
            "description": "Success",
            "content": {
              "application/json": {
                "schema": {
                  "$ref": "#/components/schemas/FriendServiceResponse"
                }
              }
            }
          }
        }
      }
    },
    "/DeleteFriend": {
      "delete": {
        "tags": [
          "User"
        ],
        "operationId": "DeleteFriend",
        "parameters": [
          {
            "name": "id",
            "in": "query",
            "style": "form",
            "schema": {
              "type": "string",
              "format": "uuid"
            }
          }
        ],
        "responses": {
          "200": {
            "description": "Success"
          }
        }
      }
    },
    "/Friends": {
      "get": {
        "tags": [
          "User"
        ],
        "operationId": "GetFriends",
        "parameters": [
          {
            "name": "userId",
            "in": "query",
            "style": "form",
            "schema": {
              "type": "integer",
              "format": "int32"
            }
          }
        ],
        "responses": {
          "200": {
            "description": "Success",
            "content": {
              "application/json": {
                "schema": {
                  "$ref": "#/components/schemas/FriendListServiceResponse"
                }
              }
            }
          }
        }
      }
    },
    "/ChangeFriendRequest": {
      "patch": {
        "tags": [
          "User"
        ],
        "operationId": "ChangeFriendRequest",
        "parameters": [
          {
            "name": "id",
            "in": "query",
            "style": "form",
            "schema": {
              "type": "string",
              "format": "uuid"
            }
          }
        ],
        "responses": {
          "200": {
            "description": "Success",
            "content": {
              "application/json": {
                "schema": {
                  "$ref": "#/components/schemas/FriendServiceResponse"
                }
              }
            }
          }
        }
      }
    }
  },
  "components": {
    "schemas": {
      "AddRoleRequest": {
        "type": "object",
        "properties": {
          "roleName": {
            "type": "string",
            "nullable": true
          },
          "description": {
            "type": "string",
            "nullable": true
          }
        },
        "additionalProperties": false
      },
      "CustomDebt": {
        "type": "object",
        "properties": {
          "id": {
            "type": "string",
            "format": "uuid"
          },
          "expenseId": {
            "type": "string",
            "format": "uuid"
          },
          "userId": {
            "type": "integer",
            "format": "int32"
          },
          "debtUserId": {
            "type": "integer",
            "format": "int32"
          },
          "debt": {
            "type": "number",
            "format": "double"
          },
          "paid": {
            "type": "number",
            "format": "double"
          }
        },
        "additionalProperties": false
      },
      "CustomDebtListServiceResponse": {
        "type": "object",
        "properties": {
          "response": {
            "type": "array",
            "items": {
              "$ref": "#/components/schemas/CustomDebt"
            },
            "nullable": true
          }
        },
        "additionalProperties": false
      },
      "DebtModel": {
        "type": "object",
        "properties": {
          "id": {
            "type": "string",
            "format": "uuid"
          },
          "expenseId": {
            "type": "string",
            "format": "uuid"
          },
          "userId": {
            "type": "integer",
            "format": "int32"
          },
          "debt": {
            "type": "number",
            "format": "double"
          },
          "paid": {
            "type": "number",
            "format": "double"
          }
        },
        "additionalProperties": false
      },
      "DebtModelListServiceResponse": {
        "type": "object",
        "properties": {
          "response": {
            "type": "array",
            "items": {
              "$ref": "#/components/schemas/DebtModel"
            },
            "nullable": true
          }
        },
        "additionalProperties": false
      },
      "DebtModelServiceResponse": {
        "type": "object",
        "properties": {
          "response": {
            "allOf": [
              {
                "$ref": "#/components/schemas/DebtModel"
              }
            ],
            "nullable": true
          }
        },
        "additionalProperties": false
      },
      "Expense": {
        "type": "object",
        "properties": {
          "id": {
            "type": "string",
            "format": "uuid"
          },
          "name": {
            "type": "string",
            "nullable": true
          },
          "userId": {
            "type": "integer",
            "format": "int32"
          },
          "groupId": {
            "type": "string",
            "format": "uuid"
          },
          "sum": {
            "type": "number",
            "format": "double"
          },
          "date": {
            "type": "string",
            "format": "date-time"
          }
        },
        "additionalProperties": false
      },
      "ExpenseListServiceResponse": {
        "type": "object",
        "properties": {
          "response": {
            "type": "array",
            "items": {
              "$ref": "#/components/schemas/Expense"
            },
            "nullable": true
          }
        },
        "additionalProperties": false
      },
      "ExpenseServiceResponse": {
        "type": "object",
        "properties": {
          "response": {
            "allOf": [
              {
                "$ref": "#/components/schemas/Expense"
              }
            ],
            "nullable": true
          }
        },
        "additionalProperties": false
      },
      "Friend": {
        "type": "object",
        "properties": {
          "id": {
            "type": "string",
            "format": "uuid"
          },
          "userId": {
            "type": "integer",
            "format": "int32"
          },
          "friendId": {
            "type": "integer",
            "format": "int32"
          },
          "request": {
            "type": "boolean"
          }
        },
        "additionalProperties": false
      },
      "FriendListServiceResponse": {
        "type": "object",
        "properties": {
          "response": {
            "type": "array",
            "items": {
              "$ref": "#/components/schemas/Friend"
            },
            "nullable": true
          }
        },
        "additionalProperties": false
      },
      "FriendServiceResponse": {
        "type": "object",
        "properties": {
          "response": {
            "allOf": [
              {
                "$ref": "#/components/schemas/Friend"
              }
            ],
            "nullable": true
          }
        },
        "additionalProperties": false
      },
      "Group": {
        "type": "object",
        "properties": {
          "id": {
            "type": "string",
            "format": "uuid"
          },
          "name": {
            "type": "string",
            "nullable": true
          },
          "date": {
            "type": "string",
            "format": "date-time"
          },
          "admin": {
            "type": "integer",
            "format": "int32"
          },
          "description": {
            "type": "string",
            "nullable": true
          },
          "members": {
            "type": "array",
            "items": {
              "$ref": "#/components/schemas/User"
            },
            "nullable": true
          }
        },
        "additionalProperties": false
      },
      "GroupListServiceResponse": {
        "type": "object",
        "properties": {
          "response": {
            "type": "array",
            "items": {
              "$ref": "#/components/schemas/Group"
            },
            "nullable": true
          }
        },
        "additionalProperties": false
      },
      "GroupMember": {
        "type": "object",
        "properties": {
          "id": {
            "type": "integer",
            "format": "int32"
          },
          "groupId": {
            "type": "string",
            "format": "uuid"
          },
          "userId": {
            "type": "integer",
            "format": "int32"
          }
        },
        "additionalProperties": false
      },
      "GroupMemberListServiceResponse": {
        "type": "object",
        "properties": {
          "response": {
            "type": "array",
            "items": {
              "$ref": "#/components/schemas/GroupMember"
            },
            "nullable": true
          }
        },
        "additionalProperties": false
      },
      "GroupServiceResponse": {
        "type": "object",
        "properties": {
          "response": {
            "allOf": [
              {
                "$ref": "#/components/schemas/Group"
              }
            ],
            "nullable": true
          }
        },
        "additionalProperties": false
      },
      "Role": {
        "type": "object",
        "properties": {
          "id": {
            "type": "integer",
            "format": "int32"
          },
          "name": {
            "type": "string",
            "nullable": true
          },
          "description": {
            "type": "string",
            "nullable": true
          }
        },
        "additionalProperties": false
      },
      "RoleListServiceResponse": {
        "type": "object",
        "properties": {
          "response": {
            "type": "array",
            "items": {
              "$ref": "#/components/schemas/Role"
            },
            "nullable": true
          }
        },
        "additionalProperties": false
      },
      "RoleServiceResponse": {
        "type": "object",
        "properties": {
          "response": {
            "allOf": [
              {
                "$ref": "#/components/schemas/Role"
              }
            ],
            "nullable": true
          }
        },
        "additionalProperties": false
      },
      "User": {
        "type": "object",
        "properties": {
          "id": {
            "type": "integer",
            "format": "int32"
          },
          "login": {
            "type": "string",
            "nullable": true
          },
          "password": {
            "type": "string",
            "nullable": true
          },
          "email": {
            "type": "string",
            "nullable": true
          },
          "name": {
            "type": "string",
            "nullable": true
          }
        },
        "additionalProperties": false
      },
      "UserListServiceResponse": {
        "type": "object",
        "properties": {
          "response": {
            "type": "array",
            "items": {
              "$ref": "#/components/schemas/User"
            },
            "nullable": true
          }
        },
        "additionalProperties": false
      },
      "UserServiceResponse": {
        "type": "object",
        "properties": {
          "response": {
            "allOf": [
              {
                "$ref": "#/components/schemas/User"
              }
            ],
            "nullable": true
          }
        },
        "additionalProperties": false
      }
    }
  }
}